watchmen_meta/__init__.py
watchmen_meta/admin/__init__.py
watchmen_meta/admin/enumeration_service.py
watchmen_meta/admin/pipeline_graphic_service.py
watchmen_meta/admin/pipeline_service.py
watchmen_meta/admin/space_service.py
watchmen_meta/admin/topic_service.py
watchmen_meta/admin/topic_snapshot_lock_service.py
watchmen_meta/admin/topic_snapshot_scheduler_service.py
watchmen_meta/admin/user_group_service.py
watchmen_meta/admin/user_service.py
watchmen_meta/analysis/__init__.py
watchmen_meta/analysis/pipeline_index_service.py
watchmen_meta/analysis/topic_index_service.py
watchmen_meta/auth/__init__.py
watchmen_meta/auth/auth_helper.py
watchmen_meta/common/__init__.py
watchmen_meta/common/exception.py
watchmen_meta/common/last_visit_service.py
watchmen_meta/common/operation_service.py
watchmen_meta/common/package_version_service.py
watchmen_meta/common/settings.py
watchmen_meta/common/storage_service.py
watchmen_meta/common/tuple_service.py
watchmen_meta/common/user_based_tuple_service.py
watchmen_meta/console/__init__.py
watchmen_meta/console/connected_space_graphic_service.py
watchmen_meta/console/connected_space_service.py
watchmen_meta/console/dashboard_service.py
watchmen_meta/console/report_service.py
watchmen_meta/console/subject_service.py
watchmen_meta/dqc/__init__.py
watchmen_meta/dqc/catalog_service.py
watchmen_meta/dqc/monitor_rule_lock_service.py
watchmen_meta/dqc/monitor_rule_service.py
watchmen_meta/gui/__init__.py
watchmen_meta/gui/favorite_service.py
watchmen_meta/gui/last_snapshot_service.py
watchmen_meta/system/__init__.py
watchmen_meta/system/ai_model_service.py
watchmen_meta/system/data_source_service.py
watchmen_meta/system/external_writer_service.py
watchmen_meta/system/key_store_service.py
watchmen_meta/system/pat_service.py
watchmen_meta/system/plugin_service.py
watchmen_meta/system/sql_query_performance_service.py
watchmen_meta/system/tenant_service.py
watchmen_meta/webhook/__init__.py
watchmen_meta/webhook/event_definition_service.py
watchmen_meta-18.0.1.dist-info/METADATA
watchmen_meta-18.0.1.dist-info/WHEEL
watchmen_meta-18.0.1.dist-info/licenses/LICENSE
watchmen_meta-18.0.1.dist-info/RECORD
